schnauzer/__init__.py
schnauzer/client.py
schnauzer/server.py
schnauzer/static/css/styles.css
schnauzer/static/favicon/android-chrome-192x192.png
schnauzer/static/favicon/android-chrome-512x512.png
schnauzer/static/favicon/apple-touch-icon.png
schnauzer/static/favicon/favicon-16x16.png
schnauzer/static/favicon/favicon-32x32.png
schnauzer/static/favicon/favicon.ico
schnauzer/static/favicon/site.webmanifest
schnauzer/static/js/app.js
schnauzer/static/js/filter.js
schnauzer/static/js/graph.js
schnauzer/static/js/interactions.js
schnauzer/static/js/layouts.js
schnauzer/static/js/search.js
schnauzer/static/js/socket.js
schnauzer/static/js/state.js
schnauzer/static/js/trace.js
schnauzer/static/js/ui.js
schnauzer/static/js/utils.js
schnauzer/templates/index.html
schnauzer-0.3.0.dist-info/licenses/LICENSE
schnauzer-0.3.0.dist-info/METADATA
schnauzer-0.3.0.dist-info/WHEEL
schnauzer-0.3.0.dist-info/entry_points.txt
schnauzer-0.3.0.dist-info/top_level.txt
schnauzer-0.3.0.dist-info/RECORD
