Metadata-Version: 2.4
Name: schnauzer
Version: 0.3.0
Summary: Visualize networkx graphs interactively in a web browser.
Author: Nico Bachmann
Author-email: python@deschnauz.ch
Requires-Python: >=3.10
License-File: LICENSE
Requires-Dist: flask
Requires-Dist: flask-socketio
Requires-Dist: pyzmq
Requires-Dist: networkx
Requires-Dist: pyyaml
Dynamic: author
Dynamic: author-email
Dynamic: description
Dynamic: description-content-type
Dynamic: license-file
Dynamic: requires-dist
Dynamic: requires-python
Dynamic: summary
